{
  "tooltip": {
    "trigger": "item"
  },
  "legend": {
    "show": true,
    "top": "3%",
    "left": "center",
    "data": [
      "虚拟现实",
      "人工智能",
      "深度学习",
      "5G技术"
    ]
  },
  "series": [
    {
      "name": "Access From",
      "type": "pie",
      "radius": "93%",
      "center": [
        "49%",
        "77%"
      ],
      "startAngle": 92,
      "endAngle": 360,
      "data": [
        {
          "value": 828,
          "name": "虚拟现实"
        },
        {
          "value": 928,
          "name": "人工智能"
        },
        {
          "value": 347,
          "name": "深度学习"
        },
        {
          "value": 397,
          "name": "5G技术"
        }
      ],
      "itemStyle": {},
      "label": {
        "show": true,
        "position": "outside",
        "formatter": "{d}%"
      }
    }
  ],
  "backgroundColor": "#fff"
}