{
  "tooltip": {
    "trigger": "item"
  },
  "legend": {
    "show": true,
    "top": "3%",
    "left": "center",
    "data": [
      "机器学习",
      "云计算",
      "数据隐私",
      "人工智能",
      "聊天机器人",
      "预测分析",
      "加密货币",
      "网络安全"
    ]
  },
  "series": [
    {
      "name": "Access From",
      "type": "pie",
      "radius": "89%",
      "center": [
        "50%",
        "75%"
      ],
      "startAngle": 90,
      "endAngle": 360,
      "data": [
        {
          "value": 776,
          "name": "机器学习"
        },
        {
          "value": 1066,
          "name": "云计算"
        },
        {
          "value": 845,
          "name": "数据隐私"
        },
        {
          "value": 1071,
          "name": "人工智能"
        },
        {
          "value": 770,
          "name": "聊天机器人"
        },
        {
          "value": 449,
          "name": "预测分析"
        },
        {
          "value": 287,
          "name": "加密货币"
        },
        {
          "value": 267,
          "name": "网络安全"
        }
      ],
      "itemStyle": {},
      "label": {
        "show": true,
        "position": "inside",
        "formatter": "{d}%"
      }
    }
  ],
  "backgroundColor": "#fff"
}